README.rst
setup.cfg
setup.py
peek_doc_dev/__init__.py
peek_doc_dev/build_html_docs.sh
peek_doc_dev/build_latex_docs.sh
peek_doc_dev/conf.py
peek_doc_dev/index.rst
peek_doc_dev/watch_docs.sh
peek_doc_dev/welcome.rst
peek_doc_dev.egg-info/PKG-INFO
peek_doc_dev.egg-info/SOURCES.txt
peek_doc_dev.egg-info/dependency_links.txt
peek_doc_dev.egg-info/not-zip-safe
peek_doc_dev.egg-info/requires.txt
peek_doc_dev.egg-info/top_level.txt
peek_doc_dev/_static/.gitkeep
peek_doc_dev/_static/fonts/fontawesome-webfont.woff2