Metadata-Version: 1.1
Name: peek-doc-dev
Version: 2.4.1
Summary: Peek Platform - Developer Documentation
Home-page: https://github.com/Synerty/peek-doc-dev
Author: Synerty
Author-email: contact@synerty.com
License: UNKNOWN
Download-URL: https://github.com/Synerty/peek-doc-dev/tarball/2.4.1
Keywords: Peek,Python,Platform,synerty
Platform: UNKNOWN
Classifier: Programming Language :: Python :: 3.5
